{
	"info": {
		"_postman_id": "d60e75a9-3394-444f-9f10-a8d0e352c09a",
		"name": "BIM 360 Document Management API Copy",
		"schema": "https://schema.getpostman.com/json/collection/v2.1.0/collection.json",
		"_exporter_id": "1440859"
	},
	"item": [
		{
			"name": "Custom Attributes",
			"item": [
				{
					"name": "01-GET one hub",
					"event": [
						{
							"listen": "test",
							"script": {
								"exec": [
									"pm.test(\"Get hub collection, Status code is 200\", function () {",
									"    pm.response.to.have.status(200);",
									"});",
									"",
									"var hub_name = pm.environment.get(\"hub_name\") ",
									"",
									"pm.test(\"find matches hub by id: \" + hub_name, function () {",
									"    var body = JSON.parse(responseBody);",
									"    var find = body.data.find(d=>d.attributes.name == hub_name)",
									"",
									"    pm.expect(find).not.eq(undefined); ",
									"    ",
									"    if(find){",
									"        pm.environment.set(\"hub_id_with_b\", find.id);",
									"        pm.environment.set(\"hub_id_without_b\", find.id.split(\"b.\").join(\"\"));",
									"    }else{",
									"        ",
									"    }",
									"    ",
									"});",
									"",
									"     "
								],
								"type": "text/javascript"
							}
						}
					],
					"request": {
						"method": "GET",
						"header": [],
						"url": {
							"raw": "{{base_domain}}/project/v1/hubs",
							"host": [
								"{{base_domain}}"
							],
							"path": [
								"project",
								"v1",
								"hubs"
							]
						},
						"description": "GET all hubs of your account, and get one hub. Please provide the hub name (hub_name) in environment variables"
					},
					"response": []
				},
				{
					"name": "02-GET one project id",
					"event": [
						{
							"listen": "test",
							"script": {
								"exec": [
									"pm.test(\"Get project collection, Status code is 200\", function () {",
									"    pm.response.to.have.status(200);",
									"});",
									"",
									"var project_name = pm.environment.get(\"project_name\") ",
									"pm.test(\"find matches project by name: \" + project_name, function () {",
									"    var body = JSON.parse(responseBody);",
									"    var find = body.data.find(d=>d.attributes.name == project_name)",
									"",
									"    pm.expect(find).not.eq(undefined); ",
									"    ",
									"    if(find){",
									"        pm.environment.set(\"project_id_with_b\", find.id);",
									"        pm.environment.set(\"project_id_without_b\", find.id.split(\"b.\").join(\"\"));",
									"        pm.environment.set(\"root_folder_id\", find.relationships.rootFolder.data.id);",
									"        ",
									"    }else{",
									"        ",
									"    }",
									"    ",
									"});",
									"",
									"     "
								],
								"type": "text/javascript"
							}
						}
					],
					"request": {
						"method": "GET",
						"header": [],
						"url": {
							"raw": "{{base_domain}}/project/v1/hubs/{{hub_id_with_b}}/projects",
							"host": [
								"{{base_domain}}"
							],
							"path": [
								"project",
								"v1",
								"hubs",
								"{{hub_id_with_b}}",
								"projects"
							]
						},
						"description": "GET all projects of one hub, and get one project Please provide the hub name (project_name) in environment variables"
					},
					"response": []
				},
				{
					"name": "03-GET [Project Files] folder id - OR manually input one_folder_id",
					"event": [
						{
							"listen": "test",
							"script": {
								"exec": [
									"pm.test(\"Get project top folder, Status code is 200\", function () {",
									"    pm.response.to.have.status(200);",
									"});",
									"",
									"pm.test(\"find [Project Files] folder id: \", function () {",
									"    var body = JSON.parse(responseBody);",
									"    var find = body.data.find(d=>d.attributes.name == \"Project Files\" )",
									"",
									"    pm.expect(find).not.eq(undefined); ",
									"    ",
									"    if(find){",
									"        pm.environment.set(\"one_folder_id\", find.id);",
									"    }else{",
									"        ",
									"    }",
									"    ",
									"});",
									"",
									"     "
								],
								"type": "text/javascript"
							}
						}
					],
					"request": {
						"method": "GET",
						"header": [],
						"url": {
							"raw": "{{base_domain}}/project/v1/hubs/{{hub_id_with_b}}/projects/{{project_id_with_b}}/topFolders",
							"host": [
								"{{base_domain}}"
							],
							"path": [
								"project",
								"v1",
								"hubs",
								"{{hub_id_with_b}}",
								"projects",
								"{{project_id_with_b}}",
								"topFolders"
							],
							"query": [
								{
									"key": "filter[attributes.name]",
									"value": "{{one_folder_name}}",
									"disabled": true
								}
							]
						},
						"description": "GET all projects of one hub, and get one project Please provide the hub name (project_name) in environment variables"
					},
					"response": []
				},
				{
					"name": "04-GET some files urn",
					"event": [
						{
							"listen": "test",
							"script": {
								"exec": [
									"pm.test(\"Get folder content of [Project Files], Status code is 200\", function () {",
									"    pm.response.to.have.status(200);",
									"});",
									"",
									"pm.test(\"find some urns: \", function () {",
									"    var body = JSON.parse(responseBody);",
									"    var find = body.data",
									"",
									"    pm.expect(find).not.eq(undefined); ",
									"    ",
									"    if(find){",
									"       ",
									"        //get version id",
									"        var demo_urn_0 = find[0].relationships.tip.data.id",
									"        var demo_urn_1 = find[1].relationships.tip.data.id",
									"        var demo_urn_2 = find[2].relationships.tip.data.id",
									"",
									"        pm.environment.set(\"demo_urn_0\", demo_urn_0);",
									"        pm.environment.set(\"demo_urn_1\", demo_urn_1);",
									"        pm.environment.set(\"demo_urn_2\", demo_urn_2);",
									"",
									"         //url encoded",
									"        pm.environment.set(\"demo_urn_0_urlencoded\", encodeURIComponent(demo_urn_0));",
									"        pm.environment.set(\"demo_urn_1_urlencoded\", encodeURIComponent(demo_urn_1));",
									"        pm.environment.set(\"demo_urn_2_urlencoded\", encodeURIComponent(demo_urn_2));",
									"    }else{",
									"        ",
									"    }",
									"    ",
									"});",
									"",
									"     "
								],
								"type": "text/javascript"
							}
						}
					],
					"request": {
						"method": "GET",
						"header": [
							{
								"key": "Authorization",
								"value": "Bearer {{access_token}}",
								"type": "text"
							}
						],
						"url": {
							"raw": "{{base_domain}}/data/v1/projects/{{project_id_with_b}}/folders/{{one_folder_id}}/contents?filter[type]=items",
							"host": [
								"{{base_domain}}"
							],
							"path": [
								"data",
								"v1",
								"projects",
								"{{project_id_with_b}}",
								"folders",
								"{{one_folder_id}}",
								"contents"
							],
							"query": [
								{
									"key": "filter[type]",
									"value": "items"
								}
							]
						}
					},
					"response": []
				},
				{
					"name": "05- GET current attributes values of some files",
					"event": [
						{
							"listen": "test",
							"script": {
								"exec": [
									"pm.test(\"Get custom attributes values of some files, Status code is 200\", function () {",
									"    pm.response.to.have.status(200);",
									"});",
									"",
									"pm.test(\"record current custom values id of one files: \", function () {",
									"    var body = JSON.parse(responseBody);",
									"    var find = body.results",
									"",
									"    pm.expect(find).not.eq(undefined); ",
									"    ",
									"    if(find){",
									"        var first_file_custom_attributes = find[0].customAttributes;",
									"        //get all ids of current custom attributes (not null)",
									"        var ids = []",
									"        for(var i=0;i<first_file_custom_attributes.length;i++){",
									"            ids.push(first_file_custom_attributes[i].id)",
									"        }",
									"        pm.environment.set(\"one_file_current_custom_attributes_ids\", JSON.stringify(ids)); ",
									"    }else{",
									"        ",
									"    }",
									"    ",
									"});",
									"",
									"     "
								],
								"type": "text/javascript"
							}
						}
					],
					"request": {
						"method": "POST",
						"header": [
							{
								"key": "Content-Type",
								"value": "application/json"
							},
							{
								"key": "x-user-id",
								"value": "BVE5MB3YCEMF",
								"type": "text",
								"disabled": true
							}
						],
						"body": {
							"mode": "raw",
							"raw": "{\n        \"urns\": [\n          \"{{demo_urn_0}}\",\n          \"{{demo_urn_1}}\",\n          \"{{demo_urn_2}}\"\n         ]\n}"
						},
						"url": {
							"raw": "{{base_domain}}/bim360/docs/v1/projects/{{project_id_without_b}}/versions:batch-get",
							"host": [
								"{{base_domain}}"
							],
							"path": [
								"bim360",
								"docs",
								"v1",
								"projects",
								"{{project_id_without_b}}",
								"versions:batch-get"
							]
						},
						"description": "https://developer.autodesk.com/api/view-and-data-api/#create-an-oauth2-token\n"
					},
					"response": []
				},
				{
					"name": "06-GET current custom attributes definition",
					"event": [
						{
							"listen": "test",
							"script": {
								"exec": [
									"pm.test(\"Get custom attributes definitions, Status code is 200\", function () {",
									"    pm.response.to.have.status(200);",
									"});",
									"",
									"pm.test(\"Get custom definitions ids: \", function () {",
									"    var body = JSON.parse(responseBody);",
									"    var find = body.results",
									"",
									"    pm.expect(find).not.eq(undefined); ",
									"    ",
									"    if(find){",
									"        //get all ids of custom attributes definitions",
									"        //assume at least 3 custom attributes types are available: text, date, dropdown",
									"        var text_custom_attribute_id = find.find(i=>i.type == \"string\").id",
									"        var date_custom_attribute_id = find.find(i=>i.type == \"date\").id",
									"        var dropdown_custom_attribute_id = find.find(i=>i.type == \"array\").id",
									"        var one_dropdown_value = find.find(i=>i.type == \"array\").arrayValues[0];",
									"",
									"        pm.environment.set(\"text_custom_attribute_id\", Number(text_custom_attribute_id)); ",
									"        pm.environment.set(\"date_custom_attribute_id\",Number(date_custom_attribute_id )); ",
									"        pm.environment.set(\"dropdown_custom_attribute_id\", Number(dropdown_custom_attribute_id)); ",
									"        pm.environment.set(\"one_dropdown_value\", one_dropdown_value); ",
									"",
									"    }else{",
									"        ",
									"    }",
									"    ",
									"});",
									"",
									"     "
								],
								"type": "text/javascript"
							}
						}
					],
					"request": {
						"method": "GET",
						"header": [],
						"url": {
							"raw": "{{base_domain}}/bim360/docs/v1/projects/{{project_id_without_b}}/folders/{{one_folder_id}}/custom-attribute-definitions",
							"host": [
								"{{base_domain}}"
							],
							"path": [
								"bim360",
								"docs",
								"v1",
								"projects",
								"{{project_id_without_b}}",
								"folders",
								"{{one_folder_id}}",
								"custom-attribute-definitions"
							],
							"query": [
								{
									"key": "limit",
									"value": "2",
									"disabled": true
								},
								{
									"key": "offset",
									"value": "4",
									"disabled": true
								}
							]
						},
						"description": "assume the folder has at least: \n\none custom attribute definition of string\n\none custom attribute definition of date\n\none custom attribute definition of array"
					},
					"response": []
				},
				{
					"name": "07-Update custom values for one file",
					"event": [
						{
							"listen": "prerequest",
							"script": {
								"exec": [
									"var d = new Date()",
									"var current_time = d.getFullYear() ",
									"                +\"-\" + ((\"0\" + (d.getUTCMonth()+1)).slice(-2) )",
									"                + \"-\" +  (\"0\" + d.getUTCDate()).slice(-2) ",
									"                ",
									"pm.environment.set(\"current_time\", current_time);",
									" "
								],
								"type": "text/javascript"
							}
						},
						{
							"listen": "test",
							"script": {
								"exec": [
									"pm.test(\"Update custom values for one file, Status code is 200\", function () {",
									"    pm.response.to.have.status(200);",
									"});"
								],
								"type": "text/javascript"
							}
						}
					],
					"request": {
						"method": "POST",
						"header": [
							{
								"key": "Content-Type",
								"value": "application/json"
							},
							{
								"key": "x-user-id",
								"value": "BVE5MB3YCEMF",
								"type": "text",
								"disabled": true
							}
						],
						"body": {
							"mode": "raw",
							"raw": "[\n                {\n                    \"id\": {{text_custom_attribute_id}}, \n                    \"value\": \"Updated Text by API\"\n                },\n                {\n                    \"id\": {{date_custom_attribute_id}}, \n                    \"value\": \"{{current_time}}\"\n                },\n               {\n                    \"id\": {{dropdown_custom_attribute_id}}, \n                    \"value\": \"{{one_dropdown_value}}\"\n                }\n]"
						},
						"url": {
							"raw": "{{base_domain}}/bim360/docs/v1/projects/{{project_id_without_b}}/versions/{{demo_urn_0_urlencoded}}/custom-attributes:batch-update",
							"host": [
								"{{base_domain}}"
							],
							"path": [
								"bim360",
								"docs",
								"v1",
								"projects",
								"{{project_id_without_b}}",
								"versions",
								"{{demo_urn_0_urlencoded}}",
								"custom-attributes:batch-update"
							]
						}
					},
					"response": []
				},
				{
					"name": "08-Create custom def - text",
					"event": [
						{
							"listen": "prerequest",
							"script": {
								"exec": [
									"const radom_string = Math.random().toString().substr(2, 8); ",
									"pm.environment.set(\"radom_string\", radom_string);",
									""
								],
								"type": "text/javascript"
							}
						},
						{
							"listen": "test",
							"script": {
								"exec": [
									"pm.test(\"Create custom def - text, Status code is 200\", function () {",
									"    pm.response.to.have.status(201);",
									"});",
									"",
									"pm.test(\"get custom definitions id: \", function () {",
									"    var body = JSON.parse(responseBody);",
									"",
									"    pm.expect(body).not.eq(undefined); ",
									"    ",
									"    if(body){  ",
									"        pm.environment.set(\"custom_def_created_by_api_text_id\", Number(body.id));   ",
									"    }else{",
									"        ",
									"    }",
									"    ",
									"});",
									"",
									"     "
								],
								"type": "text/javascript"
							}
						}
					],
					"request": {
						"method": "POST",
						"header": [
							{
								"key": "Content-Type",
								"value": "application/json"
							},
							{
								"key": "x-user-id",
								"value": "BVE5MB3YCEMF",
								"type": "text",
								"disabled": true
							}
						],
						"body": {
							"mode": "raw",
							"raw": "{\n        \"name\": \"my-column-text-{{radom_string}}\",\n        \"type\": \"string\" \n}"
						},
						"url": {
							"raw": "{{base_domain}}/bim360/docs/v1/projects/{{project_id_without_b}}/folders/{{one_folder_id}}/custom-attribute-definitions",
							"host": [
								"{{base_domain}}"
							],
							"path": [
								"bim360",
								"docs",
								"v1",
								"projects",
								"{{project_id_without_b}}",
								"folders",
								"{{one_folder_id}}",
								"custom-attribute-definitions"
							]
						}
					},
					"response": []
				},
				{
					"name": "09-Create custom def - array",
					"event": [
						{
							"listen": "prerequest",
							"script": {
								"exec": [
									"const radom_string = Math.random().toString().substr(2, 8); ",
									"pm.environment.set(\"radom_string\", radom_string);",
									""
								],
								"type": "text/javascript"
							}
						},
						{
							"listen": "test",
							"script": {
								"exec": [
									"pm.test(\"Create custom def - array, Status code is 200\", function () {",
									"    pm.response.to.have.status(201);",
									"});",
									"",
									"pm.test(\"get custom definitions id: \", function () {",
									"    var body = JSON.parse(responseBody);",
									"",
									"    pm.expect(body).not.eq(undefined); ",
									"    ",
									"    if(body){  ",
									"        pm.environment.set(\"custom_def_created_by_api_array_id\", Number(body.id));   ",
									"        pm.environment.set(\"created_by_api_value1\", \"created_by_api_value1\"); ",
									"",
									"    }else{",
									"        ",
									"    }",
									"    ",
									"});",
									"",
									"     "
								],
								"type": "text/javascript"
							}
						}
					],
					"request": {
						"method": "POST",
						"header": [
							{
								"key": "Content-Type",
								"value": "application/json"
							},
							{
								"key": "x-user-id",
								"value": "BVE5MB3YCEMF",
								"type": "text",
								"disabled": true
							}
						],
						"body": {
							"mode": "raw",
							"raw": "{\n        \"name\": \"my-column-array-{{radom_string}}\",\n        \"type\": \"array\",\n        \"arrayValues\": [\n          \"created_by_api_value1\",\n          \"created_by_api_value2\",\n          \"created_by_api_value3\"\n        ]\n}"
						},
						"url": {
							"raw": "{{base_domain}}/bim360/docs/v1/projects/{{project_id_without_b}}/folders/{{one_folder_id}}/custom-attribute-definitions",
							"host": [
								"{{base_domain}}"
							],
							"path": [
								"bim360",
								"docs",
								"v1",
								"projects",
								"{{project_id_without_b}}",
								"folders",
								"{{one_folder_id}}",
								"custom-attribute-definitions"
							]
						}
					},
					"response": []
				},
				{
					"name": "10-Create custom def - date",
					"event": [
						{
							"listen": "prerequest",
							"script": {
								"exec": [
									"const radom_string = Math.random().toString().substr(2, 8); ",
									"pm.environment.set(\"radom_string\", radom_string);",
									""
								],
								"type": "text/javascript"
							}
						},
						{
							"listen": "test",
							"script": {
								"exec": [
									"pm.test(\"Create custom def - date, Status code is 200\", function () {",
									"    pm.response.to.have.status(201);",
									"});",
									"",
									"pm.test(\"get custom definitions id: \", function () {",
									"    var body = JSON.parse(responseBody);",
									"",
									"    pm.expect(body).not.eq(undefined); ",
									"    ",
									"    if(body){  ",
									"        pm.environment.set(\"custom_def_created_by_api_date_id\", Number(body.id));   ",
									"    }else{",
									"        ",
									"    }",
									"    ",
									"});",
									"",
									"     "
								],
								"type": "text/javascript"
							}
						}
					],
					"request": {
						"method": "POST",
						"header": [
							{
								"key": "Content-Type",
								"value": "application/json"
							},
							{
								"key": "x-user-id",
								"value": "BVE5MB3YCEMF",
								"type": "text",
								"disabled": true
							}
						],
						"body": {
							"mode": "raw",
							"raw": "{\n        \"name\": \"my-column-date-{{radom_string}}\",\n        \"type\": \"date\" \n}"
						},
						"url": {
							"raw": "{{base_domain}}/bim360/docs/v1/projects/{{project_id_without_b}}/folders/{{one_folder_id}}/custom-attribute-definitions",
							"host": [
								"{{base_domain}}"
							],
							"path": [
								"bim360",
								"docs",
								"v1",
								"projects",
								"{{project_id_without_b}}",
								"folders",
								"{{one_folder_id}}",
								"custom-attribute-definitions"
							]
						}
					},
					"response": []
				},
				{
					"name": "11-GET custom attributes definition again",
					"event": [
						{
							"listen": "test",
							"script": {
								"exec": [
									"pm.test(\"Get custom attributes definitions, Status code is 200\", function () {",
									"    pm.response.to.have.status(200);",
									"});",
									"",
									"pm.test(\"record custom definitions ids: \", function () {",
									"    var body = JSON.parse(responseBody);",
									"    var find = body.results",
									"",
									"    pm.expect(find).not.eq(undefined); ",
									"    ",
									"    if(find){",
									"        //get all ids of custom attributes definitions",
									"        //assume at least 3 custom attributes types are available: text, date, dropdown",
									"        var text_custom_attribute_id = find.find(i=>i.type == \"string\").id",
									"        var date_custom_attribute_id = find.find(i=>i.type == \"date\").id",
									"        var dropdown_custom_attribute_id = find.find(i=>i.type == \"array\").id",
									"        var one_dropdown_value = find.find(i=>i.type == \"array\").arrayValues[0];",
									"",
									"        pm.environment.set(\"text_custom_attribute_id\", Number(text_custom_attribute_id)); ",
									"        pm.environment.set(\"date_custom_attribute_id\",Number(date_custom_attribute_id )); ",
									"        pm.environment.set(\"dropdown_custom_attribute_id\", Number(dropdown_custom_attribute_id)); ",
									"        pm.environment.set(\"one_dropdown_value\", one_dropdown_value); ",
									"",
									"    }else{",
									"        ",
									"    }",
									"    ",
									"});",
									"",
									"     "
								],
								"type": "text/javascript"
							}
						}
					],
					"request": {
						"method": "GET",
						"header": [],
						"url": {
							"raw": "{{base_domain}}/bim360/docs/v1/projects/{{project_id_without_b}}/folders/{{one_folder_id}}/custom-attribute-definitions",
							"host": [
								"{{base_domain}}"
							],
							"path": [
								"bim360",
								"docs",
								"v1",
								"projects",
								"{{project_id_without_b}}",
								"folders",
								"{{one_folder_id}}",
								"custom-attribute-definitions"
							],
							"query": [
								{
									"key": "limit",
									"value": "2",
									"disabled": true
								},
								{
									"key": "offset",
									"value": "4",
									"disabled": true
								}
							]
						}
					},
					"response": []
				},
				{
					"name": "12- Update custom values of NEW defs",
					"event": [
						{
							"listen": "prerequest",
							"script": {
								"exec": [
									"var d = new Date()",
									"var current_time = d.getFullYear() ",
									"                +\"-\" + ((\"0\" + (d.getUTCMonth()+1)).slice(-2) )",
									"                + \"-\" +  (\"0\" + d.getUTCDate()).slice(-2) ",
									"                ",
									"pm.environment.set(\"current_time\", current_time);",
									" "
								],
								"type": "text/javascript"
							}
						},
						{
							"listen": "test",
							"script": {
								"exec": [
									"pm.test(\"Update custom values for one file, Status code is 200\", function () {",
									"    pm.response.to.have.status(200);",
									"});"
								],
								"type": "text/javascript"
							}
						}
					],
					"request": {
						"method": "POST",
						"header": [
							{
								"key": "Content-Type",
								"value": "application/json"
							},
							{
								"key": "x-user-id",
								"value": "BVE5MB3YCEMF",
								"type": "text",
								"disabled": true
							}
						],
						"body": {
							"mode": "raw",
							"raw": "[\n                {\n                    \"id\": {{custom_def_created_by_api_text_id}}, \n                    \"value\": \"Updated Text by API\"\n                },\n                {\n                    \"id\": {{custom_def_created_by_api_date_id}}, \n                    \"value\": \"{{current_time}}\"\n                },\n               {\n                    \"id\": {{custom_def_created_by_api_array_id}}, \n                    \"value\": \"{{created_by_api_value1}}\"\n                }\n]"
						},
						"url": {
							"raw": "{{base_domain}}/bim360/docs/v1/projects/{{project_id_without_b}}/versions/{{demo_urn_0_urlencoded}}/custom-attributes:batch-update",
							"host": [
								"{{base_domain}}"
							],
							"path": [
								"bim360",
								"docs",
								"v1",
								"projects",
								"{{project_id_without_b}}",
								"versions",
								"{{demo_urn_0_urlencoded}}",
								"custom-attributes:batch-update"
							]
						}
					},
					"response": []
				},
				{
					"name": "13-Clear some custom values",
					"event": [
						{
							"listen": "prerequest",
							"script": {
								"exec": [
									"var d = new Date()",
									"var current_time = d.getFullYear() ",
									"                +\"-\" + ((\"0\" + (d.getUTCMonth()+1)).slice(-2) )",
									"                + \"-\" +  (\"0\" + d.getUTCDate()).slice(-2) ",
									"                + \"T\" +(\"0\" + d.getUTCHours()).slice(-2) ",
									"                + \":\" + (\"0\" + d.getUTCMinutes()).slice(-2) ",
									"                + \":\" + (\"0\" + d.getUTCSeconds()).slice(-2) ",
									"                + \".000Z\"",
									"pm.environment.set(\"current_time\", current_time);",
									" "
								],
								"type": "text/javascript"
							}
						},
						{
							"listen": "test",
							"script": {
								"exec": [
									"pm.test(\"Clear some custom values, Status code is 200\", function () {",
									"    pm.response.to.have.status(200);",
									"});"
								],
								"type": "text/javascript"
							}
						}
					],
					"request": {
						"method": "POST",
						"header": [
							{
								"key": "Content-Type",
								"value": "application/json"
							},
							{
								"key": "x-user-id",
								"value": "BVE5MB3YCEMF",
								"type": "text",
								"disabled": true
							}
						],
						"body": {
							"mode": "raw",
							"raw": "[\n                {\n                    \"id\": {{text_custom_attribute_id}}, \n                    \"value\": null\n                },\n                {\n                    \"id\": {{date_custom_attribute_id}}, \n                    \"value\": null\n                },\n               {\n                    \"id\": {{dropdown_custom_attribute_id}}, \n                    \"value\": null\n                }\n]"
						},
						"url": {
							"raw": "{{base_domain}}/bim360/docs/v1/projects/{{project_id_without_b}}/versions/{{demo_urn_0_urlencoded}}/custom-attributes:batch-update",
							"host": [
								"{{base_domain}}"
							],
							"path": [
								"bim360",
								"docs",
								"v1",
								"projects",
								"{{project_id_without_b}}",
								"versions",
								"{{demo_urn_0_urlencoded}}",
								"custom-attributes:batch-update"
							]
						}
					},
					"response": []
				},
				{
					"name": "14- GET current attributes values again",
					"event": [
						{
							"listen": "test",
							"script": {
								"exec": [
									"pm.test(\"Get custom attributes definitions, Status code is 200\", function () {",
									"    pm.response.to.have.status(200);",
									"});"
								],
								"type": "text/javascript"
							}
						}
					],
					"request": {
						"method": "POST",
						"header": [
							{
								"key": "Content-Type",
								"value": "application/json"
							},
							{
								"key": "x-user-id",
								"value": "BVE5MB3YCEMF",
								"type": "text",
								"disabled": true
							}
						],
						"body": {
							"mode": "raw",
							"raw": "{\n        \"urns\": [\n          \"{{demo_urn_0}}\",\n          \"{{demo_urn_1}}\",\n          \"{{demo_urn_2}}\"\n         ]\n}"
						},
						"url": {
							"raw": "{{base_domain}}/bim360/docs/v1/projects/{{project_id_without_b}}/versions:batch-get",
							"host": [
								"{{base_domain}}"
							],
							"path": [
								"bim360",
								"docs",
								"v1",
								"projects",
								"{{project_id_without_b}}",
								"versions:batch-get"
							]
						},
						"description": "https://developer.autodesk.com/api/view-and-data-api/#create-an-oauth2-token\n"
					},
					"response": []
				}
			]
		},
		{
			"name": "Download PDF",
			"item": [
				{
					"name": "01-GET one hub",
					"event": [
						{
							"listen": "test",
							"script": {
								"type": "text/javascript",
								"exec": [
									"pm.test(\"Get hub collection, Status code is 200\", function () {",
									"    pm.response.to.have.status(200);",
									"});",
									"",
									"var hub_name = pm.environment.get(\"hub_name\") ",
									"",
									"pm.test(\"find matches hub by id: \" + hub_name, function () {",
									"    var body = JSON.parse(responseBody);",
									"    var find = body.data.find(d=>d.attributes.name == hub_name)",
									"",
									"    pm.expect(find).not.eq(undefined); ",
									"    ",
									"    if(find){",
									"        pm.environment.set(\"hub_id_with_b\", find.id);",
									"        pm.environment.set(\"hub_id_without_b\", find.id.split(\"b.\").join(\"\"));",
									"    }else{",
									"        ",
									"    }",
									"    ",
									"});",
									"",
									"     "
								]
							}
						}
					],
					"request": {
						"method": "GET",
						"header": [],
						"url": {
							"raw": "{{base_domain}}/project/v1/hubs",
							"host": [
								"{{base_domain}}"
							],
							"path": [
								"project",
								"v1",
								"hubs"
							]
						},
						"description": "GET all hubs of your account, and get one hub. Please provide the hub name (hub_name) in environment variables"
					},
					"response": []
				},
				{
					"name": "02-GET one project id",
					"event": [
						{
							"listen": "test",
							"script": {
								"exec": [
									"pm.test(\"Get project collection, Status code is 200\", function () {",
									"    pm.response.to.have.status(200);",
									"});",
									"",
									"var project_name = pm.environment.get(\"project_name\") ",
									"pm.test(\"find matches project by name: \" + project_name, function () {",
									"    var body = JSON.parse(responseBody);",
									"    var find = body.data.find(d=>d.attributes.name == project_name)",
									"",
									"    pm.expect(find).not.eq(undefined); ",
									"    ",
									"    if(find){",
									"        pm.environment.set(\"project_id_with_b\", find.id);",
									"        pm.environment.set(\"project_id_without_b\", find.id.split(\"b.\").join(\"\"));",
									"        pm.environment.set(\"root_folder_id\", find.relationships.rootFolder.data.id);",
									"        ",
									"    }else{",
									"        ",
									"    }",
									"    ",
									"});",
									"",
									"     "
								],
								"type": "text/javascript"
							}
						}
					],
					"request": {
						"method": "GET",
						"header": [],
						"url": {
							"raw": "{{base_domain}}/project/v1/hubs/{{hub_id_with_b}}/projects",
							"host": [
								"{{base_domain}}"
							],
							"path": [
								"project",
								"v1",
								"hubs",
								"{{hub_id_with_b}}",
								"projects"
							]
						},
						"description": "GET all projects of one hub, and get one project Please provide the hub name (project_name) in environment variables"
					},
					"response": []
				},
				{
					"name": "03-GET [Plans] folder id - you can also manually input one_folder_id",
					"event": [
						{
							"listen": "test",
							"script": {
								"exec": [
									"pm.test(\"Get project top folder, Status code is 200\", function () {",
									"    pm.response.to.have.status(200);",
									"});",
									"",
									"pm.test(\"find [Project Files] folder id: \", function () {",
									"    var body = JSON.parse(responseBody);",
									"    var find = body.data.find(d=>d.attributes.name == \"Project Files\" )",
									"",
									"    pm.expect(find).not.eq(undefined); ",
									"    ",
									"    if(find){",
									"        pm.environment.set(\"one_folder_id\", find.id);",
									"    }else{",
									"        ",
									"    }",
									"    ",
									"});",
									"",
									"     "
								],
								"type": "text/javascript"
							}
						}
					],
					"request": {
						"method": "GET",
						"header": [],
						"url": {
							"raw": "{{base_domain}}/project/v1/hubs/{{hub_id_with_b}}/projects/{{project_id_with_b}}/topFolders",
							"host": [
								"{{base_domain}}"
							],
							"path": [
								"project",
								"v1",
								"hubs",
								"{{hub_id_with_b}}",
								"projects",
								"{{project_id_with_b}}",
								"topFolders"
							],
							"query": [
								{
									"key": "filter[attributes.name]",
									"value": "{{one_folder_name}}",
									"disabled": true
								}
							]
						},
						"description": "GET all projects of one hub, and get one project Please provide the hub name (project_name) in environment variables"
					},
					"response": []
				},
				{
					"name": "04-GET some PDF urn",
					"event": [
						{
							"listen": "test",
							"script": {
								"exec": [
									"pm.test(\"Get folder content of [Project Files], Status code is 200\", function () {",
									"    pm.response.to.have.status(200);",
									"});",
									"",
									"pm.test(\"find one PDF urn: \", function () {",
									"    var body = JSON.parse(responseBody);",
									"    var find = body.data.find(i=>i.attributes.extension.data.sourceFileName.includes(\".pdf\"))",
									"",
									"    pm.expect(find).not.eq(undefined); ",
									"    ",
									"    if(find){",
									"       ",
									"        //get version id",
									"        var demo_pdf_urn = find.relationships.tip.data.id",
									"         ",
									"         //url encoded",
									"        pm.environment.set(\"demo_pdf_urn_urlencoded\", encodeURIComponent(demo_pdf_urn));",
									"       ",
									"    }else{",
									"        ",
									"    }",
									"    ",
									"});",
									"",
									"     "
								],
								"type": "text/javascript"
							}
						}
					],
					"request": {
						"method": "GET",
						"header": [
							{
								"key": "Authorization",
								"value": "Bearer {{access_token}}",
								"type": "text"
							}
						],
						"url": {
							"raw": "{{base_domain}}/data/v1/projects/{{project_id_with_b}}/folders/{{one_folder_id}}/contents?filter[type]=items",
							"host": [
								"{{base_domain}}"
							],
							"path": [
								"data",
								"v1",
								"projects",
								"{{project_id_with_b}}",
								"folders",
								"{{one_folder_id}}",
								"contents"
							],
							"query": [
								{
									"key": "filter[type]",
									"value": "items"
								}
							]
						}
					},
					"response": []
				},
				{
					"name": "05-Start Download-include markup and includeHyperlinks",
					"event": [
						{
							"listen": "test",
							"script": {
								"exec": [
									"pm.test(\"Start Download-include markup and includeHyperlinks, Status code is 200\", function () {",
									"",
									"    var body = JSON.parse(responseBody);",
									"",
									"    pm.environment.set(\"pdf_download_id\", body.id);",
									"",
									"    pm.response.to.have.status(200);",
									"});",
									""
								],
								"type": "text/javascript"
							}
						}
					],
					"request": {
						"method": "POST",
						"header": [
							{
								"key": "Content-Type",
								"value": "application/json"
							},
							{
								"key": "Authorization",
								"value": "Bearer {{access_token}}"
							}
						],
						"body": {
							"mode": "raw",
							"raw": "{\n        \"includeMarkups\": true,\n        \"includeHyperlinks\": true\n}\n"
						},
						"url": {
							"raw": "{{base_domain}}/bim360/docs/v1/projects/{{project_id_without_b}}/versions/{{demo_pdf_urn_urlencoded}}/exports",
							"host": [
								"{{base_domain}}"
							],
							"path": [
								"bim360",
								"docs",
								"v1",
								"projects",
								"{{project_id_without_b}}",
								"versions",
								"{{demo_pdf_urn_urlencoded}}",
								"exports"
							]
						},
						"description": "https://developer.autodesk.com/api/view-and-data-api/#create-an-oauth2-token\n"
					},
					"response": []
				},
				{
					"name": "06-GET Download Status",
					"event": [
						{
							"listen": "test",
							"script": {
								"exec": [
									"pm.test(\"Get Download Status, Status code is 200\", function () {",
									"",
									"    var body = JSON.parse(responseBody);",
									"",
									"    if(body.status == \"completed\")",
									"        pm.environment.set(\"pdf_download_url\", body.data.link);",
									"    pm.response.to.have.status(200);",
									"});",
									""
								],
								"type": "text/javascript"
							}
						}
					],
					"request": {
						"method": "GET",
						"header": [
							{
								"key": "Authorization",
								"value": "Bearer {{access_token}}"
							}
						],
						"url": {
							"raw": "{{base_domain}}/bim360/docs/v1/projects/{{project_id_without_b}}/versions/{{demo_pdf_urn_urlencoded}}/exports/{{pdf_download_id}}",
							"host": [
								"{{base_domain}}"
							],
							"path": [
								"bim360",
								"docs",
								"v1",
								"projects",
								"{{project_id_without_b}}",
								"versions",
								"{{demo_pdf_urn_urlencoded}}",
								"exports",
								"{{pdf_download_id}}"
							]
						},
						"description": "https://developer.autodesk.com/api/view-and-data-api/#create-an-oauth2-token\n"
					},
					"response": []
				},
				{
					"name": "Download PDF",
					"request": {
						"method": "GET",
						"header": [
							{
								"key": "Authorization",
								"value": "Bearer {{access_token}}"
							}
						],
						"url": {
							"raw": "{{pdf_download_url}}",
							"host": [
								"{{pdf_download_url}}"
							]
						},
						"description": "https://developer.autodesk.com/api/view-and-data-api/#create-an-oauth2-token\n"
					},
					"response": []
				}
			]
		},
		{
			"name": "Folder Permission",
			"item": [
				{
					"name": "01-GET one hub",
					"event": [
						{
							"listen": "test",
							"script": {
								"type": "text/javascript",
								"exec": [
									"pm.test(\"Get hub collection, Status code is 200\", function () {",
									"    pm.response.to.have.status(200);",
									"});",
									"",
									"var hub_name = pm.environment.get(\"hub_name\") ",
									"",
									"pm.test(\"find matches hub by id: \" + hub_name, function () {",
									"    var body = JSON.parse(responseBody);",
									"    var find = body.data.find(d=>d.attributes.name == hub_name)",
									"",
									"    pm.expect(find).not.eq(undefined); ",
									"    ",
									"    if(find){",
									"        pm.environment.set(\"hub_id_with_b\", find.id);",
									"        pm.environment.set(\"hub_id_without_b\", find.id.split(\"b.\").join(\"\"));",
									"    }else{",
									"        ",
									"    }",
									"    ",
									"});",
									"",
									"     "
								]
							}
						}
					],
					"request": {
						"method": "GET",
						"header": [],
						"url": {
							"raw": "{{base_domain}}/project/v1/hubs",
							"host": [
								"{{base_domain}}"
							],
							"path": [
								"project",
								"v1",
								"hubs"
							]
						},
						"description": "GET all hubs of your account, and get one hub. Please provide the hub name (hub_name) in environment variables"
					},
					"response": []
				},
				{
					"name": "02-GET one project id",
					"event": [
						{
							"listen": "test",
							"script": {
								"exec": [
									"pm.test(\"Get project collection, Status code is 200\", function () {",
									"    pm.response.to.have.status(200);",
									"});",
									"",
									"var project_name = pm.environment.get(\"project_name\") ",
									"pm.test(\"find matches project by name: \" + project_name, function () {",
									"    var body = JSON.parse(responseBody);",
									"    var find = body.data.find(d=>d.attributes.name == project_name)",
									"",
									"    pm.expect(find).not.eq(undefined); ",
									"    ",
									"    if(find){",
									"        pm.environment.set(\"project_id_with_b\", find.id);",
									"        pm.environment.set(\"project_id_without_b\", find.id.split(\"b.\").join(\"\"));",
									"        pm.environment.set(\"root_folder_id\", find.relationships.rootFolder.data.id);",
									"        ",
									"    }else{",
									"        ",
									"    }",
									"    ",
									"});",
									"",
									"     "
								],
								"type": "text/javascript"
							}
						}
					],
					"request": {
						"method": "GET",
						"header": [],
						"url": {
							"raw": "{{base_domain}}/project/v1/hubs/{{hub_id_with_b}}/projects",
							"host": [
								"{{base_domain}}"
							],
							"path": [
								"project",
								"v1",
								"hubs",
								"{{hub_id_with_b}}",
								"projects"
							]
						},
						"description": "GET all projects of one hub, and get one project Please provide the hub name (project_name) in environment variables"
					},
					"response": []
				},
				{
					"name": "03-GET one folder id - you can also manually input one_folder_id",
					"event": [
						{
							"listen": "test",
							"script": {
								"exec": [
									"pm.test(\"Get project top folder and find one folder, Status code is 200\", function () {",
									"    pm.response.to.have.status(200);",
									"});",
									"",
									"pm.test(\"find project file folder id: \", function () {",
									"    var body = JSON.parse(responseBody);",
									"    var find = body.data.find(d=>d.attributes.name == \"Project Files\" )",
									"",
									"    pm.expect(find).not.eq(undefined); ",
									"    ",
									"    if(find){",
									"        pm.environment.set(\"one_folder_id\", find.id);",
									"    }else{",
									"        ",
									"    }",
									"    ",
									"});",
									"",
									"     "
								],
								"type": "text/javascript"
							}
						}
					],
					"request": {
						"method": "GET",
						"header": [],
						"url": {
							"raw": "{{base_domain}}/project/v1/hubs/{{hub_id_with_b}}/projects/{{project_id_with_b}}/topFolders",
							"host": [
								"{{base_domain}}"
							],
							"path": [
								"project",
								"v1",
								"hubs",
								"{{hub_id_with_b}}",
								"projects",
								"{{project_id_with_b}}",
								"topFolders"
							],
							"query": [
								{
									"key": "filter[attributes.name]",
									"value": "{{one_folder_name}}",
									"disabled": true
								}
							]
						},
						"description": "GET all projects of one hub, and get one project Please provide the hub name (project_name) in environment variables"
					},
					"response": []
				},
				{
					"name": "04-List permissions in a folder",
					"event": [
						{
							"listen": "test",
							"script": {
								"exec": [
									"pm.test(\"List project users - Status code is 200\", function () {",
									"    pm.response.to.have.status(200);",
									"});",
									"",
									"pm.test(\"find one user id: \", function () {",
									"    var body = JSON.parse(responseBody);",
									"    var find = body.results ",
									"",
									"    pm.expect(find).not.eq(undefined); ",
									"",
									"    ",
									"    pm.environment.set(\"one_user_autodeskId\", find.autodeskId); ",
									"    ",
									"});",
									"",
									"  "
								],
								"type": "text/javascript"
							}
						}
					],
					"request": {
						"method": "GET",
						"header": [
							{
								"key": "Authorization",
								"value": "Bearer {{access_token}}"
							},
							{
								"key": "x-user-id",
								"value": "BVE5MB3YCEMF"
							}
						],
						"url": {
							"raw": "{{base_domain}}/bim360/docs/v1/projects/{{project_id_without_b}}/folders/{{one_folder_id}}/permissions",
							"host": [
								"{{base_domain}}"
							],
							"path": [
								"bim360",
								"docs",
								"v1",
								"projects",
								"{{project_id_without_b}}",
								"folders",
								"{{one_folder_id}}",
								"permissions"
							]
						}
					},
					"response": []
				},
				{
					"name": "05-Get project user",
					"event": [
						{
							"listen": "test",
							"script": {
								"exec": [
									"pm.test(\"Get project user - Status code is 200\", function () {",
									"    pm.response.to.have.status(200);",
									"});",
									"",
									"pm.test(\"find one user id: \", function () {",
									"    var body = JSON.parse(responseBody);",
									"    var find = body.results ",
									"",
									"    pm.expect(find).not.eq(undefined); ",
									"",
									"    //assume at least two users in the projects. one is admin, the other is common  member",
									"    var project_admin = find.find(i=>i.accessLevels.projectAdmin == true)",
									"    var project_member = find.find(i=>i.accessLevels.projectAdmin == false)",
									"",
									"    pm.environment.set(\"project_admin_autodeskId\", project_admin.autodeskId); ",
									"    pm.environment.set(\"project_member_autodeskId\", project_member.autodeskId); ",
									"    pm.environment.set(\"project_admin_subjectId\", project_admin.id); ",
									"    pm.environment.set(\"project_member_subjectId\", project_member.id); ",
									"    ",
									"});",
									"",
									"  "
								],
								"type": "text/javascript"
							}
						},
						{
							"listen": "prerequest",
							"script": {
								"exec": [
									""
								],
								"type": "text/javascript"
							}
						}
					],
					"request": {
						"method": "GET",
						"header": [
							{
								"key": "Content-Type",
								"value": "application/json",
								"disabled": true
							},
							{
								"key": "Authorization",
								"value": "Bearer {{access_token}}"
							},
							{
								"key": "User-Id",
								"value": "200902260532621",
								"type": "text",
								"disabled": true
							}
						],
						"url": {
							"raw": "{{base_domain}}/bim360/admin/v1/projects/{{project_id_with_b}}/users",
							"host": [
								"{{base_domain}}"
							],
							"path": [
								"bim360",
								"admin",
								"v1",
								"projects",
								"{{project_id_with_b}}",
								"users"
							]
						}
					},
					"response": []
				},
				{
					"name": "05-permissions:batch-create",
					"event": [
						{
							"listen": "test",
							"script": {
								"exec": [
									"pm.test(\"permissions:batch-create - Status code is 200\", function () {",
									"    pm.response.to.have.status(200);",
									"});"
								],
								"type": "text/javascript"
							}
						}
					],
					"request": {
						"method": "POST",
						"header": [
							{
								"key": "Authorization",
								"value": "Bearer {{access_token}}"
							},
							{
								"key": "Content-Type",
								"value": "application/json"
							}
						],
						"body": {
							"mode": "raw",
							"raw": "[\n    {\n      \"subjectId\": \"{{project_member_subjectId}}\",\n      \"subjectType\": \"USER\",\n      \"actions\": [\n        \"PUBLISH\"\n      ]\n    }\n]"
						},
						"url": {
							"raw": "{{base_domain}}/bim360/docs/v1/projects/{{project_id_without_b}}/folders/{{one_folder_id}}/permissions:batch-create",
							"host": [
								"{{base_domain}}"
							],
							"path": [
								"bim360",
								"docs",
								"v1",
								"projects",
								"{{project_id_without_b}}",
								"folders",
								"{{one_folder_id}}",
								"permissions:batch-create"
							]
						}
					},
					"response": []
				},
				{
					"name": "06-permissions:batch-update",
					"event": [
						{
							"listen": "test",
							"script": {
								"exec": [
									"pm.test(\"permissions:batch-update - Status code is 200\", function () {",
									"    pm.response.to.have.status(200);",
									"});"
								],
								"type": "text/javascript"
							}
						}
					],
					"request": {
						"method": "POST",
						"header": [
							{
								"key": "Authorization",
								"value": "Bearer {{access_token}}"
							},
							{
								"key": "Content-Type",
								"value": "application/vnd.api+json"
							},
							{
								"key": "x-user-id",
								"value": "77Q5JT463CV3",
								"type": "text",
								"disabled": true
							}
						],
						"body": {
							"mode": "raw",
							"raw": "[\n        {\n          \"subjectId\": \"{{project_member_subjectId}}\",\n          \"subjectType\": \"USER\",\n          \"actions\": [\n            \"PUBLISH\",\n            \"VIEW\",\n            \"DOWNLOAD\",\n            \"COLLABORATE\",\n            \"EDIT\",\n            \"CONTROL\"\n          ]\n        }\n]"
						},
						"url": {
							"raw": "{{base_domain}}/bim360/docs/v1/projects/{{project_id_without_b}}/folders/{{one_folder_id}}/permissions:batch-update",
							"host": [
								"{{base_domain}}"
							],
							"path": [
								"bim360",
								"docs",
								"v1",
								"projects",
								"{{project_id_without_b}}",
								"folders",
								"{{one_folder_id}}",
								"permissions:batch-update"
							]
						}
					},
					"response": []
				},
				{
					"name": "07-delete permissions in a folder",
					"event": [
						{
							"listen": "test",
							"script": {
								"exec": [
									"pm.test(\"permissions:batch-delete - Status code is 200\", function () {",
									"    pm.response.to.have.status(200);",
									"});"
								],
								"type": "text/javascript"
							}
						}
					],
					"request": {
						"method": "POST",
						"header": [
							{
								"key": "Authorization",
								"value": "Bearer {{access_token}}"
							},
							{
								"key": "Content-Type",
								"value": "application/json"
							},
							{
								"key": "x-user-id",
								"value": "4V4WKQJGGQ7N",
								"disabled": true
							}
						],
						"body": {
							"mode": "raw",
							"raw": "[\n      {\n        \"subjectId\": \"{{project_member_subjectId}}\",\n        \"subjectType\": \"USER\" \n      }  \n]"
						},
						"url": {
							"raw": "{{base_domain}}/bim360/docs/v1/projects/{{project_id_without_b}}/folders/{{one_folder_id}}/permissions:batch-delete",
							"host": [
								"{{base_domain}}"
							],
							"path": [
								"bim360",
								"docs",
								"v1",
								"projects",
								"{{project_id_without_b}}",
								"folders",
								"{{one_folder_id}}",
								"permissions:batch-delete"
							]
						}
					},
					"response": []
				}
			]
		},
		{
			"name": "GET 2Legged Token",
			"event": [
				{
					"listen": "test",
					"script": {
						"exec": [
							"var data = JSON.parse(responseBody);",
							"postman.setEnvironmentVariable(\"access_token\", data.access_token);",
							"postman.setEnvironmentVariable(\"expires_in\", data.expires_in);",
							"postman.setEnvironmentVariable(\"token_type\", data.token_type);"
						],
						"type": "text/javascript",
						"packages": {}
					}
				},
				{
					"listen": "prerequest",
					"script": {
						"exec": [
							"var keys = pm.environment.get(\"client_id\") + \":\" + pm.environment.get(\"client_secret\");",
							"console.log(keys);",
							"let encodedKeys = btoa(keys); ",
							"console.log(encodedKeys)",
							"pm.environment.set(\"encodedKeys\",encodedKeys);"
						],
						"type": "text/javascript",
						"packages": {}
					}
				}
			],
			"request": {
				"auth": {
					"type": "noauth"
				},
				"method": "POST",
				"header": [
					{
						"key": "Content-Type",
						"value": "application/x-www-form-urlencoded"
					},
					{
						"key": "Authorization",
						"value": "Basic {{encodedKeys}}",
						"type": "text"
					}
				],
				"body": {
					"mode": "urlencoded",
					"urlencoded": [
						{
							"key": "grant_type",
							"value": "client_credentials",
							"type": "text"
						},
						{
							"key": "scope",
							"value": "data:write data:read",
							"type": "text"
						}
					]
				},
				"url": {
					"raw": "{{base_domain}}/authentication/v2/token",
					"host": [
						"{{base_domain}}"
					],
					"path": [
						"authentication",
						"v2",
						"token"
					]
				},
				"description": "https://developer.autodesk.com/api/view-and-data-api/#create-an-oauth2-token\n"
			},
			"response": []
		}
	],
	"auth": {
		"type": "oauth2",
		"oauth2": [
			{
				"key": "accessTokenUrl",
				"value": "https://developer.api.autodesk.com/authentication/v2/token",
				"type": "string"
			},
			{
				"key": "authUrl",
				"value": "https://developer.api.autodesk.com/authentication/v2/authorize",
				"type": "string"
			},
			{
				"key": "client_authentication",
				"value": "header",
				"type": "string"
			},
			{
				"key": "scope",
				"value": "data:read data:write",
				"type": "string"
			},
			{
				"key": "tokenName",
				"value": "access_token",
				"type": "string"
			},
			{
				"key": "challengeAlgorithm",
				"value": "S256",
				"type": "string"
			},
			{
				"key": "redirect_uri",
				"value": "https://www.getpostman.com/oauth2/callback",
				"type": "string"
			},
			{
				"key": "grant_type",
				"value": "authorization_code",
				"type": "string"
			},
			{
				"key": "clientSecret",
				"value": "{{client_secret}}",
				"type": "string"
			},
			{
				"key": "clientId",
				"value": "{{client_id}}",
				"type": "string"
			},
			{
				"key": "addTokenTo",
				"value": "header",
				"type": "string"
			},
			{
				"key": "tokenType",
				"value": "Bearer",
				"type": "string"
			}
		]
	},
	"event": [
		{
			"listen": "prerequest",
			"script": {
				"type": "text/javascript",
				"exec": [
					""
				]
			}
		},
		{
			"listen": "test",
			"script": {
				"type": "text/javascript",
				"exec": [
					""
				]
			}
		}
	]
}